{
  "domains": [
    {
      "domain": "openhost.dk",
      "history_entry": {
        "timestamp": "2026-06-18 14:13:03",
        "whois_ok": true,
        "ssl_ok": false,
        "http_status": 200,
        "http_ok": true,
        "http_response_time_ms": 1308.711,
        "resolved_ip": "91.226.144.135"
      },
      "ip_address": "20.163.63.247",
      "whois_expiry": "2027-02-26",
      "nameservers": null,
      "registrar": null,
      "ssl_expiry": "2026-05-28"
    }
  ],
  "last_updated": "18-06-2026 16:13:03",
  "ip_address": "20.163.63.247"
}