{
  "domains": [
    {
      "domain": "openhost.dk",
      "history_entry": {
        "timestamp": "2026-05-01 18:14:27",
        "whois_ok": true,
        "ssl_ok": false,
        "http_status": 200,
        "http_ok": true,
        "http_response_time_ms": 732.7470000000001,
        "resolved_ip": "91.226.144.135"
      },
      "ip_address": "48.214.54.115",
      "whois_expiry": "2027-02-26",
      "nameservers": null,
      "registrar": null,
      "ssl_expiry": "2026-05-28"
    }
  ],
  "last_updated": "01-05-2026 20:14:27",
  "ip_address": "48.214.54.115"
}